scorer/__init__.py
scorer/comparator.py
scorer/component.py
scorer/config.py
scorer/payloadreader.py
scorer/preprocesser.py
scorer/configs/__init__.py
scorer/configs/ai_keywords.txt
scorer/configs/app.properties
scorer/configs/da_keywords.txt
scorer/configs/de_keywords.txt
scorer/configs/java_patterns.txt
scorer/configs/jd_keywords.txt
scorer/configs/jfd_keywords.txt
scorer/configs/pd_keywords.txt
scorer/configs/pfd_keywords.txt
scorer/configs/python_patterns.txt
fytly-3.6.3.dist-info/LICENCE.txt
fytly-3.6.3.dist-info/METADATA
fytly-3.6.3.dist-info/WHEEL
fytly-3.6.3.dist-info/top_level.txt
fytly-3.6.3.dist-info/RECORD
