Metadata-Version: 2.1
Name: fytly
Version: 3.6.3
Summary: A grading component for keyword-based scoring for resumes
Home-page: https://www.aegletek.com/
Author: Aegletek
Author-email: coe@aegletek.com
License: MIT
Classifier: Programming Language :: Python :: 3
Classifier: Operating System :: OS Independent
Requires-Python: >=3.6
License-File: LICENCE.txt
Requires-Dist: PyPDF2
Requires-Dist: python-docx
Requires-Dist: pyspellchecker
Requires-Dist: spacy
Requires-Dist: nltk
Requires-Dist: rapidfuzz
